README.md
setup.py
ssrcli/__init__.py
ssrcli/__main__.py
ssrcli/cli.py
ssrcli/config.py
ssrcli/controllers.py
ssrcli/exceptions.py
ssrcli/log.py
ssrcli/managers.py
ssrcli/models.py
ssrcli/ssr.py
ssrcli/utils.py
ssrcli.egg-info/PKG-INFO
ssrcli.egg-info/SOURCES.txt
ssrcli.egg-info/dependency_links.txt
ssrcli.egg-info/entry_points.txt
ssrcli.egg-info/requires.txt
ssrcli.egg-info/top_level.txt
ssrcli.egg-info/zip-safe