Metadata-Version: 2.1
Name: ssrcli
Version: 3.1.2
Summary: SSR management client with shell interface
Home-page: https://github.com/myl7/ssrcli
Author: myl7
Author-email: myl7.ustc@gmail.com
License: MIT
Keywords: ssr,ssr-client
Platform: Linux
Classifier: Development Status :: 5 - Production/Stable
Classifier: Environment :: Console
Classifier: Intended Audience :: End Users/Desktop
Classifier: License :: OSI Approved :: MIT License
Classifier: Natural Language :: English
Classifier: Operating System :: POSIX :: Linux
Classifier: Programming Language :: Python :: 3
Classifier: Programming Language :: Python :: 3.6
Classifier: Programming Language :: Python :: 3.7
Classifier: Topic :: Internet :: Proxy Servers
Classifier: Typing :: Typed
Requires-Python: >=3.6
